{
    "class-declarations": [
    {
        "include": "rengine.h",
        "name": "rengine::Node",
        "alloc": "rengine::Node::create()"
    },
    {
        "include": "rengine.h",
        "name": "rengine::RectangleNode",
        "alloc": "rengine::RectangleNode::create()",
        "properties": [
            "float x",
            "float y",
            "float width",
            "float height",
            "vec4 color"
        ]
    }, {
        "include": "rengine.h",
        "name": "rengine::TextureNode",
        "alloc": "rengine::TextureNode::create()",
        "properties": [
            "float x",
            "float y",
            "float width",
            "float height",
            "rengine::Texture texture"
        ]
    }, {
        "include": "rengine.h",
        "name": "rengine::TransformNode",
        "alloc": "rengine::TransformNode::create()",
        "properties": [
            "float dx",
            "float dy",
            "float rotation",
            "float rotationAroundX",
            "float rotationAroundY",
            "float rotationAroundZ",
            "float scale",
            "float projectionDepth"
        ]
    }
    ]
}